<?xml version="1.0" encoding="UTF-8"?>
<MetaDataObject xmlns="http://v8.1c.ru/8.3/MDClasses" xmlns:app="http://v8.1c.ru/8.2/managed-application/core" xmlns:cfg="http://v8.1c.ru/8.1/data/enterprise/current-config" xmlns:cmi="http://v8.1c.ru/8.2/managed-application/cmi" xmlns:ent="http://v8.1c.ru/8.1/data/enterprise" xmlns:lf="http://v8.1c.ru/8.2/managed-application/logform" xmlns:style="http://v8.1c.ru/8.1/data/ui/style" xmlns:sys="http://v8.1c.ru/8.1/data/ui/fonts/system" xmlns:v8="http://v8.1c.ru/8.1/data/core" xmlns:v8ui="http://v8.1c.ru/8.1/data/ui" xmlns:web="http://v8.1c.ru/8.1/data/ui/colors/web" xmlns:win="http://v8.1c.ru/8.1/data/ui/colors/windows" xmlns:xen="http://v8.1c.ru/8.3/xcf/enums" xmlns:xpr="http://v8.1c.ru/8.3/xcf/predef" xmlns:xr="http://v8.1c.ru/8.3/xcf/readable" xmlns:xs="http://www.w3.org/2001/XMLSchema" xmlns:xsi="http://www.w3.org/2001/XMLSchema-instance" version="2.15">
	<ExternalReport uuid="3f08848d-a851-4476-96ec-5ee00689425d">
		<InternalInfo>
			<xr:ContainedObject>
				<xr:ClassId>e41aff26-25cf-4bb6-b6c1-3f478a75f374</xr:ClassId>
				<xr:ObjectId>f21bd154-d64d-4b67-b45e-fe1c8d6c45b5</xr:ObjectId>
			</xr:ContainedObject>
			<xr:GeneratedType name="ExternalReportObject.ВетвлениеВ_Git" category="Object">
				<xr:TypeId>155a2b2d-8cc1-4059-8566-8fae45436edd</xr:TypeId>
				<xr:ValueId>caa7b02f-c8aa-4761-91fb-27eaee01e8b8</xr:ValueId>
			</xr:GeneratedType>
		</InternalInfo>
		<Properties>
			<Name>ВетвлениеВ_Git</Name>
			<Synonym>
				<v8:item>
					<v8:lang>ru</v8:lang>
					<v8:content>Ветвление в git</v8:content>
				</v8:item>
			</Synonym>
			<Comment/>
			<DefaultForm>ExternalReport.ВетвлениеВ_Git.Form.ФормаОтчета</DefaultForm>
			<AuxiliaryForm/>
			<MainDataCompositionSchema/>
			<DefaultSettingsForm/>
			<AuxiliarySettingsForm/>
			<DefaultVariantForm/>
			<VariantsStorage/>
			<SettingsStorage/>
		</Properties>
		<ChildObjects>
			<Form>ФормаОтчета</Form>
		</ChildObjects>
	</ExternalReport>
</MetaDataObject>